UserManagerTemplate/__init__.py
UserManagerTemplate/core.py
UserManagerTemplate/log.py
UserManagerTemplate/server.py
usermanagertemplate-0.1.1.dist-info/METADATA
usermanagertemplate-0.1.1.dist-info/WHEEL
usermanagertemplate-0.1.1.dist-info/top_level.txt
usermanagertemplate-0.1.1.dist-info/RECORD
